docker_image_cleanup/__init__.py
docker_image_cleanup-0.1.0.dist-info/WHEEL
docker_image_cleanup-0.1.0.dist-info/entry_points.txt
docker_image_cleanup-0.1.0.dist-info/METADATA
docker_image_cleanup-0.1.0.dist-info/RECORD
