Metadata-Version: 2.3
Name: docker-image-cleanup
Version: 0.1.0
Summary: Clean up old Docker images from local storage with retention controls
Keywords: docker,cleanup,images,disk-space
Author: Michael Bianco
Author-email: Michael Bianco <mike@mikebian.co>
Requires-Dist: click>=8.3.0
Requires-Dist: docker>=7.1.0
Requires-Dist: structlog-config==0.6.0
Requires-Dist: whenever>=0.9.3
Requires-Python: >=3.11
Project-URL: Repository, https://github.com/iloveitaly/docker-image-cleanup
